arabic_datetime/__init__.py
arabic_datetime/_constants.py
arabic_datetime/arabic_date.py
arabic_datetime/arabic_time.py
arabic_datetime-0.1.2.dist-info/METADATA
arabic_datetime-0.1.2.dist-info/WHEEL
arabic_datetime-0.1.2.dist-info/licenses/LICENSE
arabic_datetime-0.1.2.dist-info/RECORD
