Metadata-Version: 2.3
Name: arabic-datetime
Version: 0.1.2
Summary: A simple package for formating arabic date and time.
Project-URL: Homepage, https://github.com/khaldevmedia/arabic-datetime
Project-URL: Bug Tracker, https://github.com/khaldevmedia/arabic-datetime/issues
Author-email: Khaldevmedia <khaldevmedia@gmail.com>
License-File: LICENSE
Keywords: arabic,arabic date,arabic numerals,arabic time,date,datetime,eastern arabic numerals,month names,python,time
Classifier: License :: OSI Approved :: MIT License
Classifier: Operating System :: OS Independent
Classifier: Programming Language :: Python :: 3
Requires-Python: >=3.7
